<archimate:ArchimateDiagramModel
    xmlns:xsi="http://www.w3.org/2001/XMLSchema-instance"
    xmlns:archimate="http://www.archimatetool.com/archimate"
    name="Aplicaciones_FNA_TOBE_COBIS_Procesos"
    id="3980f3c5">
  <children
      xsi:type="archimate:DiagramModelGroup"
      id="9ed95f49"
      name="Procesos de Neogcio"
      textAlignment="1">
    <bounds
        x="48"
        y="12"
        width="1429"
        height="351"/>
    <children
        xsi:type="archimate:DiagramModelArchimateObject"
        id="ef20b934">
      <sourceConnections
          xsi:type="archimate:DiagramModelArchimateConnection"
          id="89493393"
          source="ef20b934"
          target="3b130d5c">
        <archimateRelationship
            xsi:type="archimate:CompositionRelationship"
            href="CompositionRelationship_9b03b2db.xml#9b03b2db"/>
      </sourceConnections>
      <sourceConnections
          xsi:type="archimate:DiagramModelArchimateConnection"
          id="7ff94040"
          source="ef20b934"
          target="91ba90c2">
        <archimateRelationship
            xsi:type="archimate:CompositionRelationship"
            href="CompositionRelationship_ed67b732.xml#ed67b732"/>
      </sourceConnections>
      <sourceConnections
          xsi:type="archimate:DiagramModelArchimateConnection"
          id="f7b70eb0"
          source="ef20b934"
          target="7b2eb893">
        <archimateRelationship
            xsi:type="archimate:CompositionRelationship"
            href="CompositionRelationship_28f698e1.xml#28f698e1"/>
      </sourceConnections>
      <sourceConnections
          xsi:type="archimate:DiagramModelArchimateConnection"
          id="3892bf10"
          source="ef20b934"
          target="f5dca47b">
        <archimateRelationship
            xsi:type="archimate:CompositionRelationship"
            href="CompositionRelationship_aefbcb7b.xml#aefbcb7b"/>
      </sourceConnections>
      <sourceConnections
          xsi:type="archimate:DiagramModelArchimateConnection"
          id="1fc7ff8c"
          source="ef20b934"
          target="afa783a4">
        <archimateRelationship
            xsi:type="archimate:CompositionRelationship"
            href="CompositionRelationship_c7fa6682.xml#c7fa6682"/>
      </sourceConnections>
      <bounds
          x="24"
          y="36"
          width="1081"
          height="301"/>
      <children
          xsi:type="archimate:DiagramModelArchimateObject"
          id="91ba90c2"
          targetConnections="7ff94040 18bdb30f 27c9a8f9 09891620 8f7fd2f7">
        <sourceConnections
            xsi:type="archimate:DiagramModelArchimateConnection"
            id="a29722c4"
            source="91ba90c2"
            target="4783d400">
          <archimateRelationship
              xsi:type="archimate:CompositionRelationship"
              href="CompositionRelationship_ebef7239.xml#ebef7239"/>
        </sourceConnections>
        <sourceConnections
            xsi:type="archimate:DiagramModelArchimateConnection"
            id="f621d429"
            source="91ba90c2"
            target="f5dca47b">
          <archimateRelationship
              xsi:type="archimate:TriggeringRelationship"
              href="TriggeringRelationship_5a861b7a.xml#5a861b7a"/>
        </sourceConnections>
        <sourceConnections
            xsi:type="archimate:DiagramModelArchimateConnection"
            id="9f2c4f1e"
            source="91ba90c2"
            target="7b2eb893">
          <bendpoints
              startX="84"
              startY="84"
              endX="-354"/>
          <archimateRelationship
              xsi:type="archimate:TriggeringRelationship"
              href="TriggeringRelationship_88da375d.xml#88da375d"/>
        </sourceConnections>
        <sourceConnections
            xsi:type="archimate:DiagramModelArchimateConnection"
            id="47ba0150"
            source="91ba90c2"
            target="4e61da08">
          <archimateRelationship
              xsi:type="archimate:TriggeringRelationship"
              href="TriggeringRelationship_f983b991.xml#f983b991"/>
        </sourceConnections>
        <bounds
            x="24"
            y="96"
            width="409"
            height="97"/>
        <children
            xsi:type="archimate:DiagramModelArchimateObject"
            id="4783d400"
            targetConnections="a29722c4">
          <bounds
              x="12"
              y="36"
              width="120"
              height="55"/>
          <archimateElement
              xsi:type="archimate:BusinessProcess"
              href="BusinessProcess_ff116b91.xml#ff116b91"/>
        </children>
        <children
            xsi:type="archimate:DiagramModelArchimateObject"
            id="8cbc946c">
          <bounds
              x="144"
              y="36"
              width="120"
              height="55"/>
          <archimateElement
              xsi:type="archimate:BusinessProcess"
              href="BusinessProcess_190975bf.xml#190975bf"/>
        </children>
        <children
            xsi:type="archimate:DiagramModelArchimateObject"
            id="b1ab808b">
          <bounds
              x="276"
              y="36"
              width="120"
              height="55"/>
          <archimateElement
              xsi:type="archimate:BusinessProcess"
              href="BusinessProcess_0183f67a.xml#0183f67a"/>
        </children>
        <archimateElement
            xsi:type="archimate:BusinessProcess"
            href="BusinessProcess_431cd5f8.xml#431cd5f8"/>
      </children>
      <children
          xsi:type="archimate:DiagramModelArchimateObject"
          id="f5dca47b"
          targetConnections="f621d429 3892bf10 7f36c51d">
        <sourceConnections
            xsi:type="archimate:DiagramModelArchimateConnection"
            id="36923d42"
            source="f5dca47b"
            target="a6ac732d">
          <archimateRelationship
              xsi:type="archimate:TriggeringRelationship"
              href="TriggeringRelationship_72b8885b.xml#72b8885b"/>
        </sourceConnections>
        <bounds
            x="469"
            y="156"
            width="120"
            height="55"/>
        <archimateElement
            xsi:type="archimate:BusinessProcess"
            href="BusinessProcess_db57181f.xml#db57181f"/>
      </children>
      <children
          xsi:type="archimate:DiagramModelArchimateObject"
          id="7b2eb893"
          targetConnections="81ba498d 9f2c4f1e f7b70eb0 e0684012">
        <sourceConnections
            xsi:type="archimate:DiagramModelArchimateConnection"
            id="28646444"
            source="7b2eb893"
            target="afa783a4">
          <archimateRelationship
              xsi:type="archimate:TriggeringRelationship"
              href="TriggeringRelationship_496ac8d9.xml#496ac8d9"/>
        </sourceConnections>
        <bounds
            x="624"
            y="216"
            width="157"
            height="49"/>
        <archimateElement
            xsi:type="archimate:BusinessProcess"
            href="BusinessProcess_515636ba.xml#515636ba"/>
      </children>
      <children
          xsi:type="archimate:DiagramModelArchimateObject"
          id="afa783a4"
          targetConnections="b70b8295 28646444 1fc7ff8c">
        <sourceConnections
            xsi:type="archimate:DiagramModelArchimateConnection"
            id="b253902c"
            source="afa783a4"
            target="3b130d5c">
          <archimateRelationship
              xsi:type="archimate:TriggeringRelationship"
              href="TriggeringRelationship_0fb91712.xml#0fb91712"/>
        </sourceConnections>
        <bounds
            x="816"
            y="96"
            width="120"
            height="55"/>
        <archimateElement
            xsi:type="archimate:BusinessProcess"
            href="BusinessProcess_4e4121e2.xml#4e4121e2"/>
      </children>
      <children
          xsi:type="archimate:DiagramModelArchimateObject"
          id="3b130d5c"
          targetConnections="b253902c 89493393 585cc655">
        <bounds
            x="948"
            y="96"
            width="120"
            height="55"/>
        <archimateElement
            xsi:type="archimate:BusinessProcess"
            href="BusinessProcess_a8ff7219.xml#a8ff7219"/>
      </children>
      <children
          xsi:type="archimate:DiagramModelArchimateObject"
          id="a6ac732d"
          targetConnections="888f0708 36923d42">
        <sourceConnections
            xsi:type="archimate:DiagramModelArchimateConnection"
            id="b70b8295"
            source="a6ac732d"
            target="afa783a4">
          <archimateRelationship
              xsi:type="archimate:TriggeringRelationship"
              href="TriggeringRelationship_272190a8.xml#272190a8"/>
        </sourceConnections>
        <sourceConnections
            xsi:type="archimate:DiagramModelArchimateConnection"
            id="81ba498d"
            source="a6ac732d"
            target="7b2eb893">
          <archimateRelationship
              xsi:type="archimate:TriggeringRelationship"
              href="TriggeringRelationship_f52dc946.xml#f52dc946"/>
        </sourceConnections>
        <bounds
            x="624"
            y="96"
            width="133"
            height="55"/>
        <archimateElement
            xsi:type="archimate:BusinessProcess"
            href="BusinessProcess_73ec066b.xml#73ec066b"/>
      </children>
      <children
          xsi:type="archimate:DiagramModelArchimateObject"
          id="4e61da08"
          targetConnections="47ba0150 66f65e42">
        <sourceConnections
            xsi:type="archimate:DiagramModelArchimateConnection"
            id="888f0708"
            source="4e61da08"
            target="a6ac732d">
          <archimateRelationship
              xsi:type="archimate:TriggeringRelationship"
              href="TriggeringRelationship_c8a1f2fd.xml#c8a1f2fd"/>
        </sourceConnections>
        <bounds
            x="469"
            y="36"
            width="120"
            height="55"/>
        <archimateElement
            xsi:type="archimate:BusinessProcess"
            href="BusinessProcess_6ec0792c.xml#6ec0792c"/>
      </children>
      <archimateElement
          xsi:type="archimate:BusinessProcess"
          href="BusinessProcess_c28fd64f.xml#c28fd64f"/>
    </children>
    <children
        xsi:type="archimate:DiagramModelArchimateObject"
        id="0c548446">
      <bounds
          x="1128"
          y="36"
          width="265"
          height="301"/>
      <children
          xsi:type="archimate:DiagramModelArchimateObject"
          id="9c5ed540"
          targetConnections="d7757f86">
        <bounds
            x="76"
            y="113"
            width="120"
            height="55"/>
        <archimateElement
            xsi:type="archimate:BusinessProcess"
            href="BusinessProcess_71ffd38d.xml#71ffd38d"/>
      </children>
      <archimateElement
          xsi:type="archimate:BusinessProcess"
          href="BusinessProcess_c656baba.xml#c656baba"/>
    </children>
  </children>
  <children
      xsi:type="archimate:DiagramModelGroup"
      id="240ce2dc"
      name="Aplicaciones Core / Backend"
      textAlignment="1">
    <bounds
        x="46"
        y="396"
        width="1431"
        height="337"/>
    <children
        xsi:type="archimate:DiagramModelArchimateObject"
        id="16035022">
      <sourceConnections
          xsi:type="archimate:DiagramModelArchimateConnection"
          id="ef9c4682"
          source="16035022"
          target="ea68cffd">
        <archimateRelationship
            xsi:type="archimate:CompositionRelationship"
            href="CompositionRelationship_53ddfd46.xml#53ddfd46"/>
      </sourceConnections>
      <bounds
          x="516"
          y="48"
          width="493"
          height="265"/>
      <children
          xsi:type="archimate:DiagramModelArchimateObject"
          id="ea68cffd"
          targetConnections="ef9c4682">
        <sourceConnections
            xsi:type="archimate:DiagramModelArchimateConnection"
            id="18bdb30f"
            source="ea68cffd"
            target="91ba90c2">
          <bendpoints
              startX="2"
              startY="-123"
              endX="360"
              endY="192"/>
          <bendpoints
              startX="-274"
              startY="-123"
              endX="84"
              endY="192"/>
          <archimateRelationship
              xsi:type="archimate:ServingRelationship"
              href="ServingRelationship_98754092.xml#98754092"/>
        </sourceConnections>
        <bounds
            x="36"
            y="36"
            width="120"
            height="55"/>
        <archimateElement
            xsi:type="archimate:ApplicationComponent"
            href="ApplicationComponent_76d9a749.xml#76d9a749"/>
      </children>
      <children
          xsi:type="archimate:DiagramModelArchimateObject"
          id="9583ce21">
        <sourceConnections
            xsi:type="archimate:DiagramModelArchimateConnection"
            id="585cc655"
            source="9583ce21"
            target="3b130d5c">
          <bendpoints
              startX="14"
              startY="-123"
              endX="-252"
              endY="213"/>
          <bendpoints
              startX="278"
              startY="-123"
              endX="12"
              endY="213"/>
          <archimateRelationship
              xsi:type="archimate:ServingRelationship"
              href="ServingRelationship_75a347fb.xml#75a347fb"/>
        </sourceConnections>
        <bounds
            x="192"
            y="36"
            width="120"
            height="55"/>
        <archimateElement
            xsi:type="archimate:ApplicationComponent"
            href="ApplicationComponent_a91c4c04.xml#a91c4c04"/>
      </children>
      <children
          xsi:type="archimate:DiagramModelArchimateObject"
          id="5a8eaa72">
        <sourceConnections
            xsi:type="archimate:DiagramModelArchimateConnection"
            id="7f36c51d"
            source="5a8eaa72"
            target="f5dca47b">
          <bendpoints
              startX="14"
              startY="-123"
              endX="371"
              endY="153"/>
          <bendpoints
              startX="-358"
              startY="-123"
              endX="-1"
              endY="153"/>
          <archimateRelationship
              xsi:type="archimate:ServingRelationship"
              href="ServingRelationship_7ddce53f.xml#7ddce53f"/>
        </sourceConnections>
        <bounds
            x="360"
            y="36"
            width="120"
            height="55"/>
        <archimateElement
            xsi:type="archimate:ApplicationComponent"
            href="ApplicationComponent_5f604a98.xml#5f604a98"/>
      </children>
      <children
          xsi:type="archimate:DiagramModelArchimateObject"
          id="1b9a87b9">
        <sourceConnections
            xsi:type="archimate:DiagramModelArchimateConnection"
            id="66f65e42"
            source="1b9a87b9"
            target="4e61da08">
          <bendpoints
              startX="74"
              startY="-3"
              endX="131"
              endY="477"/>
          <bendpoints
              startX="74"
              startY="-207"
              endX="131"
              endY="273"/>
          <bendpoints
              startX="14"
              startY="-207"
              endX="71"
              endY="273"/>
          <bendpoints
              startX="14"
              startY="-423"
              endX="71"
              endY="57"/>
          <archimateRelationship
              xsi:type="archimate:ServingRelationship"
              href="ServingRelationship_4f8f935a.xml#4f8f935a"/>
        </sourceConnections>
        <bounds
            x="36"
            y="120"
            width="120"
            height="55"/>
        <archimateElement
            xsi:type="archimate:ApplicationComponent"
            href="ApplicationComponent_65bd3f16.xml#65bd3f16"/>
      </children>
      <children
          xsi:type="archimate:DiagramModelArchimateObject"
          id="418096dc">
        <sourceConnections
            xsi:type="archimate:DiagramModelArchimateConnection"
            id="e0684012"
            source="418096dc"
            target="7b2eb893">
          <bendpoints
              startX="86"
              startY="-3"
              endX="126"
              endY="300"/>
          <bendpoints
              startX="86"
              startY="-219"
              endX="126"
              endY="84"/>
          <bendpoints
              startX="-22"
              startY="-219"
              endX="18"
              endY="84"/>
          <archimateRelationship
              xsi:type="archimate:ServingRelationship"
              href="ServingRelationship_e0b040cd.xml#e0b040cd"/>
        </sourceConnections>
        <bounds
            x="192"
            y="120"
            width="120"
            height="55"/>
        <archimateElement
            xsi:type="archimate:ApplicationComponent"
            href="ApplicationComponent_e63f8a1b.xml#e63f8a1b"/>
      </children>
      <children
          xsi:type="archimate:DiagramModelArchimateObject"
          id="8aef9b27">
        <sourceConnections
            xsi:type="archimate:DiagramModelArchimateConnection"
            id="d7757f86"
            source="8aef9b27"
            target="9c5ed540">
          <bendpoints
              startX="338"
              startY="-3"
              endX="8"
              endY="400"/>
          <archimateRelationship
              xsi:type="archimate:ServingRelationship"
              href="ServingRelationship_41d085a3.xml#41d085a3"/>
        </sourceConnections>
        <bounds
            x="360"
            y="120"
            width="120"
            height="55"/>
        <archimateElement
            xsi:type="archimate:ApplicationComponent"
            href="ApplicationComponent_43173750.xml#43173750"/>
      </children>
      <children
          xsi:type="archimate:DiagramModelArchimateObject"
          id="412f3b9c">
        <sourceConnections
            xsi:type="archimate:DiagramModelArchimateConnection"
            id="8f7fd2f7"
            source="412f3b9c"
            target="91ba90c2">
          <bendpoints
              startX="-214"
              startY="-3"
              endX="144"
              endY="468"/>
          <archimateRelationship
              xsi:type="archimate:ServingRelationship"
              href="ServingRelationship_7e2f8d93.xml#7e2f8d93"/>
        </sourceConnections>
        <bounds
            x="36"
            y="192"
            width="120"
            height="55"/>
        <archimateElement
            xsi:type="archimate:ApplicationComponent"
            href="ApplicationComponent_cf827465.xml#cf827465"/>
      </children>
      <children
          xsi:type="archimate:DiagramModelArchimateObject"
          id="630b1996">
        <bounds
            x="192"
            y="192"
            width="120"
            height="55"/>
        <archimateElement
            xsi:type="archimate:ApplicationComponent"
            href="ApplicationComponent_0e490dc3.xml#0e490dc3"/>
      </children>
      <children
          xsi:type="archimate:DiagramModelArchimateObject"
          id="81f40480">
        <bounds
            x="360"
            y="192"
            width="120"
            height="55"/>
        <archimateElement
            xsi:type="archimate:ApplicationComponent"
            href="ApplicationComponent_205ff53b.xml#205ff53b"/>
      </children>
      <archimateElement
          xsi:type="archimate:ApplicationComponent"
          href="ApplicationComponent_f74bd30e.xml#f74bd30e"/>
    </children>
    <children
        xsi:type="archimate:DiagramModelArchimateObject"
        id="1671b59b">
      <sourceConnections
          xsi:type="archimate:DiagramModelArchimateConnection"
          id="27c9a8f9"
          source="1671b59b"
          target="91ba90c2">
        <archimateRelationship
            xsi:type="archimate:ServingRelationship"
            href="ServingRelationship_9a105b2b.xml#9a105b2b"/>
      </sourceConnections>
      <bounds
          x="36"
          y="48"
          width="120"
          height="55"/>
      <archimateElement
          xsi:type="archimate:ApplicationComponent"
          href="ApplicationComponent_ab5672ee.xml#ab5672ee"/>
    </children>
    <children
        xsi:type="archimate:DiagramModelArchimateObject"
        id="692dc021">
      <sourceConnections
          xsi:type="archimate:DiagramModelArchimateConnection"
          id="09891620"
          source="692dc021"
          target="91ba90c2">
        <archimateRelationship
            xsi:type="archimate:ServingRelationship"
            href="ServingRelationship_cc6cb1b5.xml#cc6cb1b5"/>
      </sourceConnections>
      <bounds
          x="216"
          y="48"
          width="120"
          height="55"/>
      <archimateElement
          xsi:type="archimate:ApplicationComponent"
          href="ApplicationComponent_350a1a20.xml#350a1a20"/>
    </children>
  </children>
</archimate:ArchimateDiagramModel>
